[{"_id":"5d7d71ded1485322948bb4be","ciclo":"13","cliente":"Abuela","producto":56766,"cantidad":1,"precio":255,"porGanancia":30,"puntos":8,"notas":"Rep Humor i","createdAt":"2019-09-14T23:03:58.204Z","updatedAt":"2019-09-14T23:03:58.204Z","__v":0},{"_id":"5d7d7251d1485322948bb4bf","ciclo":"13","cliente":"Abuela","producto":68647,"cantidad":1,"precio":340,"porGanancia":30,"puntos":10,"notas":"Jabon liquido maracuya","createdAt":"2019-09-14T23:05:53.093Z","updatedAt":"2019-09-14T23:05:53.093Z","__v":0},{"_id":"5d7d729cd1485322948bb4c0","ciclo":"13","cliente":"Euge","producto":69034,"cantidad":1,"precio":382,"porGanancia":30,"puntos":12,"notas":"base 3 en 1","createdAt":"2019-09-14T23:07:08.040Z","updatedAt":"2019-09-14T23:07:08.040Z","__v":0},{"_id":"5d7d72dad1485322948bb4c1","ciclo":"13","cliente":"Euge","producto":65763,"cantidad":1,"precio":255,"porGanancia":30,"puntos":8,"notas":"rep kaiak","createdAt":"2019-09-14T23:08:10.616Z","updatedAt":"2019-09-14T23:08:10.616Z","__v":0},{"_id":"5d7d730ad1485322948bb4c2","ciclo":"13","cliente":"Mama","producto":27371,"cantidad":1,"precio":425,"porGanancia":30,"puntos":13,"notas":"delineador retractil","createdAt":"2019-09-14T23:08:58.266Z","updatedAt":"2019-09-14T23:08:58.266Z","__v":0},{"_id":"5d7d7345d1485322948bb4c3","ciclo":"13","cliente":"Mama","producto":59880,"cantidad":1,"precio":1305,"porGanancia":30,"puntos":40,"notas":"chronos crema","createdAt":"2019-09-14T23:09:57.485Z","updatedAt":"2019-09-14T23:09:57.485Z","__v":0},{"_id":"5d7d73aed1485322948bb4c4","ciclo":"13","cliente":"yo","producto":76689,"cantidad":1,"precio":707,"porGanancia":0,"puntos":30,"notas":"broncer","createdAt":"2019-09-14T23:11:42.967Z","updatedAt":"2019-09-14T23:11:42.967Z","__v":0},{"_id":"5d7d73ffd1485322948bb4c5","ciclo":"13","cliente":"sere","producto":92170,"cantidad":1,"precio":371,"porGanancia":0,"puntos":16,"notas":"labial velvet petalo ","createdAt":"2019-09-14T23:13:03.038Z","updatedAt":"2019-09-14T23:13:03.038Z","__v":0}]